novocontrol_toolbox/__init__.py
novocontrol_toolbox/basicE.py
novocontrol_toolbox/measurement_scrambler.py
novocontrol_toolbox/novo_toolbox.py
novocontrol_toolbox/plot_utils.py
novocontrol_toolbox-2.1.dist-info/METADATA
novocontrol_toolbox-2.1.dist-info/WHEEL
novocontrol_toolbox-2.1.dist-info/licenses/LICENSE
novocontrol_toolbox-2.1.dist-info/RECORD
