Metadata-Version: 2.4
Name: novocontrol_toolbox
Version: 2.1
Summary: Python module to assist working with measurement .TXT files generated by Novocontrol instruments.
Project-URL: Homepage, https://github.com/quirin053/novocontrol_toolbox
Project-URL: Issues, https://github.com/quirin053/novocontrol_toolbox/issues
Author-email: Quirin Möller <quirin.moeller@tum.de>
License-Expression: MIT
License-File: LICENSE
Classifier: Intended Audience :: Science/Research
Classifier: Operating System :: OS Independent
Classifier: Programming Language :: Python :: 3
Classifier: Topic :: Scientific/Engineering
Requires-Python: >=3.12
Requires-Dist: matplotlib
Requires-Dist: numpy
Requires-Dist: pandas
